constellation/__init__.py
constellation/constellation.py
constellation_enum-0.1.0.dist-info/licenses/LICENSE
constellation_enum-0.1.0.dist-info/METADATA
constellation_enum-0.1.0.dist-info/WHEEL
constellation_enum-0.1.0.dist-info/top_level.txt
constellation_enum-0.1.0.dist-info/RECORD
