Metadata-Version: 2.4
Name: constellation-enum
Version: 0.1.0
Summary: A Python enum for astronomical constellations with standard abbreviations
Home-page: https://github.com/gomeshun/constellation-enum
Author: Shunichi Horigome
Author-email: Shunichi Horigome <shunichi.horigome@gmail.com>
License-Expression: MIT
Project-URL: Homepage, https://github.com/gomeshun/constellation-enum
Project-URL: Bug Reports, https://github.com/gomeshun/constellation-enum/issues
Project-URL: Source, https://github.com/gomeshun/constellation-enum
Keywords: astronomy,constellation,enum,abbreviation
Classifier: Development Status :: 4 - Beta
Classifier: Intended Audience :: Science/Research
Classifier: Intended Audience :: Education
Classifier: Topic :: Scientific/Engineering :: Astronomy
Classifier: Programming Language :: Python :: 3
Classifier: Programming Language :: Python :: 3.8
Classifier: Programming Language :: Python :: 3.9
Classifier: Programming Language :: Python :: 3.10
Classifier: Programming Language :: Python :: 3.11
Classifier: Programming Language :: Python :: 3.12
Requires-Python: >=3.8
License-File: LICENSE
Dynamic: author
Dynamic: home-page
Dynamic: license-file
Dynamic: requires-python
